cheshire_cat_api/__init__.py
cheshire_cat_api/api/__init__.py
cheshire_cat_api/api/embedder_api.py
cheshire_cat_api/api/large_language_model_api.py
cheshire_cat_api/api/memory_api.py
cheshire_cat_api/api/plugins_api.py
cheshire_cat_api/api/rabbit_hole_api.py
cheshire_cat_api/api/settings_api.py
cheshire_cat_api/api/status_api.py
cheshire_cat_api/api_client.py
cheshire_cat_api/api_response.py
cheshire_cat_api/cat_client.py
cheshire_cat_api/config.py
cheshire_cat_api/configuration.py
cheshire_cat_api/exceptions.py
cheshire_cat_api/models/__init__.py
cheshire_cat_api/models/body_upload_url.py
cheshire_cat_api/models/http_validation_error.py
cheshire_cat_api/models/location_inner.py
cheshire_cat_api/models/setting_body.py
cheshire_cat_api/models/validation_error.py
cheshire_cat_api/models/value.py
cheshire_cat_api/py.typed
cheshire_cat_api/rest.py
cheshire_cat_api-1.4.9.dist-info/METADATA
cheshire_cat_api-1.4.9.dist-info/WHEEL
cheshire_cat_api-1.4.9.dist-info/RECORD
