Metadata-Version: 2.3
Name: cheshire_cat_api
Version: 1.4.9
Summary: 😸 Cheshire-Cat API Client
License: GPL-3.0-only
Keywords: OpenAPI,Cheshire-Cat,LLM,OpenSource
Author: Chesire Cat AI
Maintainer: Nicola Corbellini
Requires-Python: >=3.10,<4.0
Classifier: Development Status :: 3 - Alpha
Classifier: Framework :: FastAPI
Classifier: License :: OSI Approved :: GNU General Public License v3 (GPLv3)
Classifier: Programming Language :: Python :: 3
Classifier: Programming Language :: Python :: 3.10
Classifier: Programming Language :: Python :: 3.11
Classifier: Programming Language :: Python :: 3.12
Classifier: Programming Language :: Python :: 3.13
Classifier: Topic :: Scientific/Engineering :: Artificial Intelligence
Requires-Dist: pydantic (>=2)
Requires-Dist: python-dateutil (>=2.5.3)
Requires-Dist: urllib3 (>=1.25.3,<2.1.0)
Requires-Dist: websocket-client (>=1.6.1)
Project-URL: Homepage, https://cheshirecat.ai/
Project-URL: Repository, https://github.com/cheshire-cat-ai/cheshire-cat-api
